{"sorts": ["object", "label"], "predicates": {"above": ["object", "object"], "brown": ["object"], "gray": ["object"], "has_label": ["object", "label"], "below": ["object", "object"], "green": ["object"], "IN": ["object", "object"], "in front of": ["object", "object"], "crooked": ["object"], "metal": ["object"], "beneath": ["object", "object"], "white": ["object"]}, "interpretation": {"above": [["571494_2_1", "571495_0_171"], ["571494_2_1", "571508_0_237"]], "brown": [["571495_0_171"], ["571497_258_327"], ["571500_168_247"]], "gray": [["571494_2_1"]], "has_label": [["571494_2_1", "sky"], ["571495_0_171", "tree"], ["571496_1_263", "field"], ["571497_258_327", "pile"], ["571508_0_237", "fence"], ["571500_168_247", "fence post"], ["571504_182_253", "sheep"]], "below": [["571496_1_263", "571494_2_1"]], "green": [["571496_1_263"]], "IN": [["571497_258_327", "571496_1_263"]], "in front of": [["571496_1_263", "571508_0_237"], ["571496_1_263", "571508_0_237"], ["571500_168_247", "571504_182_253"]], "crooked": [["571508_0_237"]], "metal": [["571508_0_237"]], "beneath": [["571496_1_263", "571494_2_1"], ["571496_1_263", "571494_2_1"], ["571497_258_327", "571494_2_1"]], "white": [["571504_182_253"]]}, "elements": {"object": ["571494_2_1", "571495_0_171", "571496_1_263", "571497_258_327", "571504_182_253", "571508_0_237", "571500_168_247"], "label": ["sky", "fence post", "fence", "field", "pile", "sheep", "tree"]}, "image": {"id": 2376588, "url": "https://cs.stanford.edu/people/rak248/VG_100K/2376588.jpg", "width": 500, "height": 374, "coco_id": null, "flickr_id": 5436513713}}