{"sorts": ["object", "label"], "predicates": {"left": ["object", "object"], "right": ["object", "object"], "front": ["object", "object"], "disequal": ["object", "object"], "has_label": ["object", "label"], "cyan": ["object"], "metal": ["object"], "small": ["object"], "same_color": ["object", "object"], "same_material": ["object", "object"], "same_size": ["object", "object"], "behind": ["object", "object"], "yellow": ["object"], "rubber": ["object"]}, "elements": {"object": ["4-0", "4-1", "4-2", "4-3"], "label": ["cube", "cylinder"]}, "interpretation": {"left": [["4-1", "4-0"], ["4-2", "4-0"], ["4-1", "4-2"], ["4-0", "4-3"], ["4-1", "4-3"], ["4-2", "4-3"]], "right": [["4-3", "4-0"], ["4-0", "4-1"], ["4-2", "4-1"], ["4-3", "4-1"], ["4-0", "4-2"], ["4-3", "4-2"]], "front": [["4-2", "4-0"], ["4-3", "4-0"], ["4-2", "4-1"], ["4-3", "4-1"]], "disequal": [["4-1", "4-0"], ["4-0", "4-1"], ["4-3", "4-2"], ["4-2", "4-3"]], "has_label": [["4-0", "cube"], ["4-1", "cube"], ["4-2", "cylinder"], ["4-3", "cylinder"]], "cyan": [["4-0"], ["4-1"]], "metal": [["4-0"], ["4-1"]], "small": [["4-0"], ["4-1"], ["4-2"], ["4-3"]], "same_color": [["4-1", "4-0"], ["4-0", "4-1"], ["4-3", "4-2"], ["4-2", "4-3"]], "same_material": [["4-1", "4-0"], ["4-0", "4-1"], ["4-3", "4-2"], ["4-2", "4-3"]], "same_size": [["4-1", "4-0"], ["4-2", "4-0"], ["4-3", "4-0"], ["4-0", "4-1"], ["4-2", "4-1"], ["4-3", "4-1"], ["4-0", "4-2"], ["4-1", "4-2"], ["4-3", "4-2"], ["4-0", "4-3"], ["4-1", "4-3"], ["4-2", "4-3"]], "behind": [["4-0", "4-2"], ["4-1", "4-2"], ["4-0", "4-3"], ["4-1", "4-3"]], "yellow": [["4-2"], ["4-3"]], "rubber": [["4-2"], ["4-3"]]}, "raw": {"scene": [{"id": "4-0", "position": [1.245615005493164, 0.17703765630722046, 0.3453257083892822], "color": "cyan", "material": "metal", "shape": "cube", "size": "small"}, {"id": "4-1", "position": [-1.472583293914795, -0.0354776605963707, 0.3482329845428467], "color": "cyan", "material": "metal", "shape": "cube", "size": "small"}, {"id": "4-2", "position": [-0.16994544863700867, 1.3502310514450073, 0.35275891423225403], "color": "yellow", "material": "rubber", "shape": "cylinder", "size": "small"}, {"id": "4-3", "position": [2.7010562419891357, 1.5804369449615479, 0.3498579263687134], "color": "yellow", "material": "rubber", "shape": "cylinder", "size": "small"}]}}