{"scenes": [{"split": "val", "directions": {"front": [0.754490315914154, -0.6563112735748291, -0.0], "right": [0.6563112735748291, 0.7544902563095093, -0.0], "above": [0.0, 0.0, 1.0], "behind": [-0.754490315914154, 0.6563112735748291, 0.0], "left": [-0.6563112735748291, -0.7544902563095093, 0.0], "below": [-0.0, -0.0, -1.0]}, "relationships": {"front": [[], []], "left": [[], [0]], "right": [[1], []], "behind": [[], []]}, "image_filename": "CLEVR_val_000000.png", "image_index": 0, "objects": [{"pixel_coords": [237, 131, 10.88541316986084], "material": "metal", "size": "large", "color": "gray", "shape": "sphere", "3d_coords": [0.0, -0.07999999821186066, 0.699999988079071], "rotation": 0.0}, {"pixel_coords": [372, 135, 10.728435516357422], "material": "metal", "size": "large", "color": "gray", "shape": "cylinder", "3d_coords": [1.9500000476837158, 1.8899999856948853, 0.699999988079071], "rotation": 0.0}]}, {"split": "val", "directions": {"front": [0.754490315914154, -0.6563112735748291, -0.0], "right": [0.6563112735748291, 0.7544902563095093, -0.0], "above": [0.0, 0.0, 1.0], "behind": [-0.754490315914154, 0.6563112735748291, 0.0], "left": [-0.6563112735748291, -0.7544902563095093, 0.0], "below": [-0.0, -0.0, -1.0]}, "relationships": {"front": [[1, 2], [], []], "left": [[], [0], [0, 1]], "right": [[1, 2], [2], []], "behind": [[], [0], [0]]}, "image_filename": "CLEVR_val_000001.png", "image_index": 1, "objects": [{"pixel_coords": [114, 124, 11.202706336975098], "material": "metal", "size": "large", "color": "gray", "shape": "cylinder", "3d_coords": [-2.0, -1.8300000429153442, 0.699999988079071], "rotation": 0.0}, {"pixel_coords": [243, 129, 10.984496116638184], "material": "metal", "size": "large", "color": "cyan", "shape": "cylinder", "3d_coords": [-0.009999999776482582, 0.07999999821186066, 0.699999988079071], "rotation": 0.0}, {"pixel_coords": [383, 133, 10.813097953796387], "material": "metal", "size": "large", "color": "gray", "shape": "sphere", "3d_coords": [2.0399999618530273, 2.140000104904175, 0.699999988079071], "rotation": 0.0}]}, {"split": "val", "directions": {"front": [0.754490315914154, -0.6563112735748291, -0.0], "right": [0.6563112735748291, 0.7544902563095093, -0.0], "above": [0.0, 0.0, 1.0], "behind": [-0.754490315914154, 0.6563112735748291, 0.0], "left": [-0.6563112735748291, -0.7544902563095093, 0.0], "below": [-0.0, -0.0, -1.0]}, "relationships": {"front": [[2], [2], []], "left": [[], [0], [0, 1]], "right": [[1, 2], [2], []], "behind": [[], [], [0, 1]]}, "image_filename": "CLEVR_val_000002.png", "image_index": 2, "objects": [{"pixel_coords": [101, 128, 11.054219245910645], "material": "metal", "size": "large", "color": "gray", "shape": "sphere", "3d_coords": [-2.0199999809265137, -2.109999895095825, 0.699999988079071], "rotation": 0.0}, {"pixel_coords": [235, 130, 10.950102806091309], "material": "metal", "size": "large", "color": "gray", "shape": "cylinder", "3d_coords": [-0.07999999821186066, -0.05999999865889549, 0.699999988079071], "rotation": 0.0}, {"pixel_coords": [373, 136, 10.703597068786621], "material": "metal", "size": "large", "color": "cyan", "shape": "sphere", "3d_coords": [1.9700000286102295, 1.8700000047683716, 0.699999988079071], "rotation": 0.0}]}, {"split": "val", "directions": {"front": [0.754490315914154, -0.6563112735748291, -0.0], "right": [0.6563112735748291, 0.7544902563095093, -0.0], "above": [0.0, 0.0, 1.0], "behind": [-0.754490315914154, 0.6563112735748291, 0.0], "left": [-0.6563112735748291, -0.7544902563095093, 0.0], "below": [-0.0, -0.0, -1.0]}, "relationships": {"front": [[3], [3], [], []], "left": [[], [0], [0, 1], [0, 1, 2]], "right": [[1, 2, 3], [2, 3], [3], []], "behind": [[], [], [], [0, 1]]}, "image_filename": "CLEVR_val_000003.png", "image_index": 3, "objects": [{"pixel_coords": [104, 141, 11.301421165466309], "material": "metal", "size": "small", "color": "purple", "shape": "sphere", "3d_coords": [-2.0899999141693115, -2.049999952316284, 0.3499999940395355], "rotation": 0.0}, {"pixel_coords": [171, 141, 11.269584655761719], "material": "metal", "size": "small", "color": "purple", "shape": "cylinder", "3d_coords": [-1.1200000047683716, -0.9900000095367432, 0.3499999940395355], "rotation": 0.0}, {"pixel_coords": [240, 144, 11.17305850982666], "material": "metal", "size": "small", "color": "purple", "shape": "sphere", "3d_coords": [-0.07000000029802322, 0.05000000074505806, 0.3499999940395355], "rotation": 0.0}, {"pixel_coords": [307, 147, 11.02367115020752], "material": "metal", "size": "small", "color": "purple", "shape": "sphere", "3d_coords": [0.9900000095367432, 1.0099999904632568, 0.3499999940395355], "rotation": 0.0}]}, {"split": "val", "directions": {"front": [0.754490315914154, -0.6563112735748291, -0.0], "right": [0.6563112735748291, 0.7544902563095093, -0.0], "above": [0.0, 0.0, 1.0], "behind": [-0.754490315914154, 0.6563112735748291, 0.0], "left": [-0.6563112735748291, -0.7544902563095093, 0.0], "below": [-0.0, -0.0, -1.0]}, "relationships": {"front": [[2, 3], [3], [], []], "left": [[], [0], [0, 1], [0, 1, 2]], "right": [[1, 2, 3], [2, 3], [3], []], "behind": [[], [], [0], [0, 1]]}, "image_filename": "CLEVR_val_000004.png", "image_index": 4, "objects": [{"pixel_coords": [88, 126, 11.109626770019531], "material": "metal", "size": "large", "color": "gray", "shape": "cube", "3d_coords": [-2.259999990463257, -2.2899999618530273, 0.699999988079071], "rotation": 0.0}, {"pixel_coords": [170, 129, 10.970976829528809], "material": "metal", "size": "large", "color": "brown", "shape": "sphere", "3d_coords": [-0.9900000095367432, -1.0700000524520874, 0.699999988079071], "rotation": 0.0}, {"pixel_coords": [308, 132, 10.846071243286133], "material": "metal", "size": "large", "color": "brown", "shape": "cylinder", "3d_coords": [0.9900000095367432, 0.9900000095367432, 0.699999988079071], "rotation": 0.0}, {"pixel_coords": [401, 136, 10.705419540405273], "material": "metal", "size": "large", "color": "brown", "shape": "sphere", "3d_coords": [2.3499999046325684, 2.309999942779541, 0.699999988079071], "rotation": 0.0}]}, {"split": "val", "directions": {"front": [0.754490315914154, -0.6563112735748291, -0.0], "right": [0.6563112735748291, 0.7544902563095093, -0.0], "above": [0.0, 0.0, 1.0], "behind": [-0.754490315914154, 0.6563112735748291, 0.0], "left": [-0.6563112735748291, -0.7544902563095093, 0.0], "below": [-0.0, -0.0, -1.0]}, "relationships": {"front": [[2], [2], []], "left": [[], [0], [0, 1]], "right": [[1, 2], [2], []], "behind": [[], [], [0, 1]]}, "image_filename": "CLEVR_val_000005.png", "image_index": 5, "objects": [{"pixel_coords": [110, 123, 11.246013641357422], "material": "metal", "size": "large", "color": "yellow", "shape": "sphere", "3d_coords": [-2.0999999046325684, -1.8700000047683716, 0.699999988079071], "rotation": 0.0}, {"pixel_coords": [241, 126, 11.105504035949707], "material": "metal", "size": "large", "color": "yellow", "shape": "cylinder", "3d_coords": [-0.14000000059604645, 0.14000000059604645, 0.699999988079071], "rotation": 0.0}, {"pixel_coords": [371, 131, 10.90808391571045], "material": "metal", "size": "large", "color": "cyan", "shape": "cube", "3d_coords": [1.809999942779541, 2.0399999618530273, 0.699999988079071], "rotation": 0.0}]}], "info": {"split": "val", "date": "07/09/2022", "license": "Creative Commons Attribution (CC-BY 4.0)", "version": "1.0"}}