{"sorts": ["object", "label"], "predicates": {"has_label": ["object", "label"], "gray": ["object"], "stainless_steel": ["object"], "blue": ["object"], "black": ["object"], "white": ["object"], "silver": ["object"], "wood": ["object"], "rectangular": ["object"], "open": ["object"], "floral": ["object"], "steel": ["object"], "square": ["object"], "tan": ["object"], "on": ["object", "object"], "to_the_left_of": ["object", "object"], "to_the_right_of": ["object", "object"]}, "elements": {"object": ["1219324", "1219339", "1219329", "1219327", "1219326", "1219337", "1219323", "1219332", "1219333", "1219345", "1219334", "1219335", "1219330", "1219344", "1219347", "1219346", "1219341", "1219340", "1219343", "1219342"], "label": ["lamp", "cabinets", "comforter", "ottoman", "bench", "ceiling", "window", "refrigerator", "paper_towels", "stove", "end_table", "countertop", "microwave", "pantry", "door", "magnets", "window", "pillows", "floor", "pillow"]}, "interpretation": {"has_label": [["1219324", "lamp"], ["1219339", "cabinets"], ["1219329", "comforter"], ["1219327", "ottoman"], ["1219326", "bench"], ["1219337", "ceiling"], ["1219323", "window"], ["1219332", "refrigerator"], ["1219333", "paper_towels"], ["1219345", "stove"], ["1219334", "end_table"], ["1219335", "countertop"], ["1219330", "microwave"], ["1219344", "pantry"], ["1219347", "door"], ["1219346", "magnets"], ["1219341", "window"], ["1219340", "pillows"], ["1219343", "floor"], ["1219342", "pillow"]], "gray": [["1219342"]], "stainless_steel": [["1219332"]], "blue": [["1219329"]], "black": [["1219332"]], "white": [["1219333"], ["1219347"]], "silver": [["1219330"]], "wood": [["1219339"], ["1219343"]], "rectangular": [["1219327"]], "open": [["1219344"]], "floral": [["1219327"]], "steel": [["1219330"]], "square": [["1219323"]], "tan": [["1219327"]], "on": [["1219346", "1219332"]], "to_the_left_of": [["1219339", "1219330"], ["1219329", "1219342"], ["1219327", "1219326"], ["1219337", "1219341"], ["1219332", "1219324"], ["1219333", "1219346"], ["1219333", "1219332"], ["1219345", "1219332"], ["1219345", "1219333"], ["1219335", "1219324"], ["1219330", "1219332"], ["1219344", "1219342"], ["1219344", "1219341"], ["1219344", "1219324"], ["1219344", "1219334"], ["1219347", "1219335"], ["1219347", "1219333"], ["1219347", "1219330"], ["1219347", "1219344"], ["1219347", "1219345"], ["1219341", "1219323"], ["1219342", "1219324"]], "to_the_right_of": [["1219324", "1219332"], ["1219324", "1219335"], ["1219324", "1219342"], ["1219324", "1219344"], ["1219326", "1219327"], ["1219323", "1219341"], ["1219332", "1219333"], ["1219332", "1219330"], ["1219332", "1219345"], ["1219333", "1219347"], ["1219333", "1219345"], ["1219345", "1219347"], ["1219334", "1219344"], ["1219335", "1219347"], ["1219330", "1219339"], ["1219330", "1219347"], ["1219344", "1219347"], ["1219346", "1219333"], ["1219341", "1219344"], ["1219341", "1219337"], ["1219342", "1219329"], ["1219342", "1219344"]]}}