{"sorts": ["object", "label"], "predicates": {"has_label": ["object", "label"], "brick": ["object"], "bending": ["object"], "gray": ["object"], "grazing": ["object"], "blue": ["object"], "black": ["object"], "standing": ["object"], "brown": ["object"], "eating": ["object"], "sandy": ["object"], "wood": ["object"], "metal": ["object"], "long": ["object"], "large": ["object"], "green": ["object"], "down": ["object"], "below": ["object", "object"], "behind": ["object", "object"], "standing_near": ["object", "object"], "to_the_right_of": ["object", "object"], "in_front_of": ["object", "object"], "beside": ["object", "object"], "to_the_left_of": ["object", "object"], "by": ["object", "object"], "on": ["object", "object"], "near": ["object", "object"]}, "elements": {"object": ["636391", "636392", "636379", "636383", "636378", "636393", "636382", "636390", "636380", "636381", "636386", "636387", "636384", "636385", "636377", "636388", "636389", "636375", "636394"], "label": ["trees", "head", "ground", "rocks", "sky", "neck", "log", "fence", "building", "bush", "pole", "door", "grass", "basket", "zebra", "building", "trees", "giraffe", "palm_tree"]}, "interpretation": {"has_label": [["636391", "trees"], ["636392", "head"], ["636379", "ground"], ["636383", "rocks"], ["636378", "sky"], ["636393", "neck"], ["636382", "log"], ["636390", "fence"], ["636380", "building"], ["636381", "bush"], ["636386", "pole"], ["636387", "door"], ["636384", "grass"], ["636385", "basket"], ["636377", "zebra"], ["636388", "building"], ["636389", "trees"], ["636375", "giraffe"], ["636394", "palm_tree"]], "brick": [["636390"]], "bending": [["636377"]], "gray": [["636382"]], "grazing": [["636377"]], "blue": [["636378"]], "black": [["636377"]], "standing": [["636375"]], "brown": [["636375"]], "eating": [["636377"], ["636375"]], "sandy": [["636379"]], "wood": [["636382"]], "metal": [["636385"]], "long": [["636393"]], "large": [["636383"], ["636375"]], "green": [["636384"]], "down": [["636392"]], "below": [["636379", "636378"]], "behind": [["636390", "636389"], ["636380", "636381"], ["636377", "636383"]], "standing_near": [["636377", "636375"]], "to_the_right_of": [["636391", "636389"], ["636391", "636388"], ["636379", "636392"], ["636379", "636377"], ["636393", "636389"], ["636382", "636379"], ["636390", "636388"], ["636390", "636387"], ["636380", "636375"], ["636380", "636393"], ["636380", "636391"], ["636381", "636393"], ["636381", "636386"], ["636381", "636375"], ["636386", "636391"], ["636386", "636393"], ["636386", "636385"], ["636386", "636375"], ["636385", "636393"], ["636389", "636388"], ["636375", "636390"], ["636375", "636388"], ["636375", "636389"], ["636375", "636377"]], "in_front_of": [["636383", "636377"], ["636381", "636380"], ["636389", "636390"]], "beside": [["636383", "636384"], ["636382", "636381"]], "to_the_left_of": [["636391", "636386"], ["636391", "636380"], ["636392", "636379"], ["636379", "636382"], ["636393", "636385"], ["636393", "636386"], ["636393", "636381"], ["636393", "636380"], ["636390", "636375"], ["636386", "636381"], ["636387", "636390"], ["636385", "636386"], ["636377", "636375"], ["636377", "636379"], ["636388", "636391"], ["636388", "636375"], ["636388", "636389"], ["636388", "636390"], ["636389", "636393"], ["636389", "636391"], ["636389", "636375"], ["636375", "636380"], ["636375", "636381"], ["636375", "636386"]], "by": [["636382", "636375"]], "on": [["636385", "636386"]], "near": [["636377", "636394"], ["636394", "636377"]]}}