{"sorts": ["object", "label"], "predicates": {"left": ["object", "object"], "behind": ["object", "object"], "disequal": ["object", "object"], "has_label": ["object", "label"], "blue": ["object"], "metal": ["object"], "large": ["object"], "same_color": ["object", "object"], "same_material": ["object", "object"], "same_size": ["object", "object"], "right": ["object", "object"], "front": ["object", "object"], "brown": ["object"], "rubber": ["object"], "small": ["object"]}, "elements": {"object": ["4-0", "4-1", "4-2", "4-3"], "label": ["sphere", "cube"]}, "interpretation": {"left": [["4-1", "4-0"], ["4-2", "4-0"], ["4-3", "4-0"], ["4-1", "4-2"], ["4-1", "4-3"], ["4-2", "4-3"]], "behind": [["4-2", "4-0"], ["4-3", "4-0"], ["4-2", "4-1"], ["4-3", "4-1"]], "disequal": [["4-1", "4-0"], ["4-0", "4-1"], ["4-3", "4-2"], ["4-2", "4-3"]], "has_label": [["4-0", "cube"], ["4-1", "cube"], ["4-2", "sphere"], ["4-3", "sphere"]], "blue": [["4-0"], ["4-1"]], "metal": [["4-0"], ["4-1"]], "large": [["4-0"], ["4-1"]], "same_color": [["4-1", "4-0"], ["4-0", "4-1"], ["4-3", "4-2"], ["4-2", "4-3"]], "same_material": [["4-1", "4-0"], ["4-0", "4-1"], ["4-3", "4-2"], ["4-2", "4-3"]], "same_size": [["4-1", "4-0"], ["4-0", "4-1"], ["4-3", "4-2"], ["4-2", "4-3"]], "right": [["4-0", "4-1"], ["4-2", "4-1"], ["4-3", "4-1"], ["4-0", "4-2"], ["4-3", "4-2"], ["4-0", "4-3"]], "front": [["4-0", "4-2"], ["4-1", "4-2"], ["4-0", "4-3"], ["4-1", "4-3"]], "brown": [["4-2"], ["4-3"]], "rubber": [["4-2"], ["4-3"]], "small": [["4-2"], ["4-3"]]}, "raw": {"scene": [{"id": "4-0", "position": [2.116243839263916, 2.0986082553863525, 0.7053171396255493], "color": "blue", "material": "metal", "shape": "cube", "size": "large"}, {"id": "4-1", "position": [-0.028737477958202362, 2.064727544784546, 0.7024372220039368], "color": "blue", "material": "metal", "shape": "cube", "size": "large"}, {"id": "4-2", "position": [0.2877415120601654, -2.777928113937378, 0.35092198848724365], "color": "brown", "material": "rubber", "shape": "sphere", "size": "small"}, {"id": "4-3", "position": [1.5818599462509155, -2.663510322570801, 0.3487838804721832], "color": "brown", "material": "rubber", "shape": "sphere", "size": "small"}]}}