{"sorts": ["object", "label"], "predicates": {"has_label": ["object", "label"], "red": ["object"], "sweet": ["object"], "plastic": ["object"], "narrow": ["object"], "green": ["object"], "stone": ["object"], "empty": ["object"], "yellow": ["object"], "wrapped": ["object"], "round": ["object"], "large": ["object"], "metal": ["object"], "bunched": ["object"], "below": ["object", "object"], "piled_on": ["object", "object"], "to_the_right_of": ["object", "object"], "of": ["object", "object"], "above": ["object", "object"], "on_top_of": ["object", "object"], "to_the_left_of": ["object", "object"], "underneath": ["object", "object"], "behind": ["object", "object"], "carrying": ["object", "object"]}, "elements": {"object": ["1333517", "1333516", "1333515", "1333514", "1333513", "1333511", "1333522", "1333523", "1333519", "1333518", "1333520", "1333521"], "label": ["pineapples", "newspaper", "tomatoes", "pan", "bananas", "sign", "tray", "street", "asparagus", "display", "woman", "bowl"]}, "interpretation": {"has_label": [["1333517", "pineapples"], ["1333516", "newspaper"], ["1333515", "tomatoes"], ["1333514", "pan"], ["1333513", "bananas"], ["1333511", "sign"], ["1333522", "tray"], ["1333523", "street"], ["1333519", "asparagus"], ["1333518", "display"], ["1333520", "woman"], ["1333521", "bowl"]], "red": [["1333511"]], "sweet": [["1333513"]], "plastic": [["1333518"]], "narrow": [["1333523"]], "green": [["1333518"]], "stone": [["1333523"]], "empty": [["1333514"]], "yellow": [["1333513"]], "wrapped": [["1333515"]], "round": [["1333522"]], "large": [["1333514"]], "metal": [["1333514"]], "bunched": [["1333513"]], "below": [["1333516", "1333515"]], "piled_on": [["1333515", "1333516"]], "to_the_right_of": [["1333517", "1333523"], ["1333516", "1333511"], ["1333515", "1333511"], ["1333514", "1333517"], ["1333514", "1333518"], ["1333511", "1333513"]], "of": [["1333516", "1333515"], ["1333518", "1333517"]], "above": [["1333515", "1333516"]], "on_top_of": [["1333515", "1333516"]], "to_the_left_of": [["1333517", "1333514"], ["1333513", "1333511"], ["1333511", "1333515"], ["1333511", "1333516"], ["1333523", "1333517"], ["1333518", "1333514"]], "underneath": [["1333516", "1333515"]], "behind": [["1333514", "1333518"]], "carrying": [["1333520", "1333521"]]}}