{"sorts": ["object", "label"], "predicates": {"has_label": ["object", "label"], "blue": ["object"], "nike": ["object"], "white": ["object"], "green": ["object"], "behind": ["object", "object"], "to_the_right_of": ["object", "object"], "to_the_left_of": ["object", "object"], "on": ["object", "object"], "in_front_of": ["object", "object"], "swinging": ["object", "object"], "watching": ["object", "object"], "holding": ["object", "object"], "next_to": ["object", "object"], "near": ["object", "object"], "wearing": ["object", "object"]}, "elements": {"object": ["465890", "465891", "465892", "465893", "465889", "465888", "465887", "465886", "465885", "465879", "465883", "465882", "465881", "465880", "465878"], "label": ["shirt", "hat", "wall", "logo", "hand", "shorts", "wrist", "watch", "ball", "racket", "logo", "man", "shorts", "shirt", "man"]}, "interpretation": {"has_label": [["465890", "shirt"], ["465891", "hat"], ["465892", "wall"], ["465893", "logo"], ["465889", "hand"], ["465888", "shorts"], ["465887", "wrist"], ["465886", "watch"], ["465885", "ball"], ["465879", "racket"], ["465883", "logo"], ["465882", "man"], ["465881", "shorts"], ["465880", "shirt"], ["465878", "man"]], "blue": [["465891"], ["465888"]], "nike": [["465893"]], "white": [["465890"], ["465881"]], "green": [["465885"], ["465883"], ["465880"]], "behind": [["465878", "465882"]], "to_the_right_of": [["465890", "465878"], ["465890", "465880"], ["465889", "465885"], ["465888", "465893"], ["465888", "465878"], ["465888", "465881"], ["465882", "465880"], ["465882", "465878"], ["465882", "465885"], ["465882", "465889"], ["465882", "465893"], ["465882", "465881"], ["465881", "465883"], ["465880", "465887"], ["465880", "465886"], ["465878", "465883"]], "to_the_left_of": [["465893", "465882"], ["465893", "465888"], ["465889", "465882"], ["465887", "465880"], ["465886", "465880"], ["465885", "465882"], ["465885", "465889"], ["465883", "465878"], ["465883", "465881"], ["465881", "465888"], ["465881", "465882"], ["465880", "465882"], ["465880", "465890"], ["465878", "465890"], ["465878", "465882"], ["465878", "465888"]], "on": [["465886", "465887"], ["465883", "465892"]], "in_front_of": [["465882", "465878"]], "swinging": [["465878", "465879"]], "watching": [["465882", "465878"]], "holding": [["465878", "465879"]], "next_to": [["465879", "465885"]], "near": [["465885", "465879"]], "wearing": [["465878", "465881"]]}}