{"sorts": ["object", "label"], "predicates": {"placed on": ["object", "object"], "wooden": ["object"], "light": ["object"], "light brown": ["object"], "small": ["object"], "beautiful": ["object"], "pretty": ["object"], "nice": ["object"], "colorful": ["object"], "healthy": ["object"], "attractive": ["object"], "purple": ["object"], "violet": ["object"], "pink": ["object"], "white": ["object"], "bright pink": ["object"], "has_label": ["object", "label"], "with": ["object", "object"], "brown": ["object"], "tall": ["object"], "has": ["object", "object"], "have": ["object", "object"], "green": ["object"], "bright green": ["object"], "long": ["object"], "skinny": ["object"], "against": ["object", "object"], "plain": ["object"], "neutral white": ["object"], "hanging from": ["object", "object"], "little": ["object"], "falling down": ["object"], "IN": ["object", "object"], "ON": ["object", "object"], "next to": ["object", "object"], "filled with": ["object", "object"], "in a": ["object", "object"], "on bottom of": ["object", "object"], "OF": ["object", "object"], "on a": ["object", "object"]}, "interpretation": {"placed on": [["453674_162_45", "453675_43_290"], ["453674_162_45", "453675_43_290"], ["453674_162_45", "453675_43_290"], ["453674_162_45", "453675_43_290"], ["453674_162_45", "453675_43_290"], ["453674_162_45", "453675_43_290"], ["453674_162_45", "453675_43_290"], ["453674_162_45", "453675_43_290"], ["453674_162_45", "453675_43_290"]], "wooden": [["453675_43_290"]], "light": [["453675_43_290"]], "light brown": [["453675_43_290"]], "small": [["453675_43_290"], ["453674_162_45"]], "beautiful": [["453674_162_45"]], "pretty": [["453674_162_45"]], "nice": [["453674_162_45"]], "colorful": [["453674_162_45"]], "healthy": [["453674_162_45"]], "attractive": [["453674_162_45"]], "purple": [["453674_162_45"], ["453681_187_160"]], "violet": [["453674_162_45"]], "pink": [["453674_162_45"]], "white": [["453674_162_45"], ["453676_210_167"], ["453678_1_1"]], "bright pink": [["453674_162_45"]], "has_label": [["453674_162_45", "flowers"], ["453675_43_290", "table"], ["453676_210_167", "vase"], ["453677_212_239", "design"], ["453679_190_79", "stems"], ["453680_171_90", "leaves"], ["453678_1_1", "wall"], ["453681_187_160", "bunch of flowers"]], "with": [["453676_210_167", "453674_162_45"], ["453676_210_167", "453674_162_45"], ["453676_210_167", "453674_162_45"]], "brown": [["453676_210_167"], ["453677_212_239"]], "tall": [["453676_210_167"]], "has": [["453676_210_167", "453677_212_239"], ["453676_210_167", "453677_212_239"]], "have": [["453674_162_45", "453679_190_79"], ["453674_162_45", "453680_171_90"], ["453674_162_45", "453679_190_79"], ["453674_162_45", "453680_171_90"], ["453674_162_45", "453679_190_79"], ["453674_162_45", "453679_190_79"]], "green": [["453679_190_79"], ["453680_171_90"]], "bright green": [["453679_190_79"]], "long": [["453679_190_79"], ["453680_171_90"]], "skinny": [["453680_171_90"]], "against": [["453676_210_167", "453678_1_1"]], "plain": [["453678_1_1"]], "neutral white": [["453678_1_1"]], "hanging from": [["453681_187_160", "453676_210_167"]], "little": [["453681_187_160"]], "falling down": [["453681_187_160"]], "IN": [["453674_162_45", "453676_210_167"]], "ON": [["453676_210_167", "453675_43_290"], ["453677_212_239", "453676_210_167"], ["453677_212_239", "453676_210_167"]], "next to": [["453675_43_290", "453678_1_1"]], "filled with": [["453676_210_167", "453674_162_45"]], "in a": [["453674_162_45", "453676_210_167"]], "on bottom of": [["453677_212_239", "453676_210_167"]], "OF": [["453676_210_167", "453674_162_45"]], "on a": [["453676_210_167", "453675_43_290"]]}, "elements": {"object": ["453675_43_290", "453676_210_167", "453680_171_90", "453679_190_79", "453674_162_45", "453681_187_160", "453678_1_1", "453677_212_239"], "label": ["stems", "wall", "bunch of flowers", "vase", "leaves", "design", "flowers", "table"]}, "image": {"id": 2395507, "url": "https://cs.stanford.edu/people/rak248/VG_100K_2/2395507.jpg", "width": 500, "height": 333, "coco_id": null, "flickr_id": 4685782043}}