{"sorts": ["object", "label"], "predicates": {"has_label": ["object", "label"], "black": ["object"], "tiny": ["object"], "white": ["object"], "of": ["object", "object"], "to_the_left_of": ["object", "object"], "to_the_right_of": ["object", "object"]}, "elements": {"object": ["1703866", "2632208", "2234751", "2355100", "2602940", "2472397", "1946407", "1665197", "2044287", "2325469"], "label": ["flowers", "trunk", "ground", "mane", "zebra", "nose", "grass", "rock", "eye", "mouth"]}, "interpretation": {"has_label": [["1703866", "flowers"], ["2632208", "trunk"], ["2234751", "ground"], ["2355100", "mane"], ["2602940", "zebra"], ["2472397", "nose"], ["1946407", "grass"], ["1665197", "rock"], ["2044287", "eye"], ["2325469", "mouth"]], "black": [["2472397"], ["2044287"], ["2325469"]], "tiny": [["1703866"]], "white": [["1703866"], ["2355100"], ["2602940"]], "of": [["2355100", "2602940"], ["2472397", "2602940"]], "to_the_left_of": [["2602940", "2234751"]], "to_the_right_of": [["2234751", "2602940"]]}}