{"sorts": ["object", "label"], "predicates": {"left": ["object", "object"], "has_label": ["object", "label"], "brown": ["object"], "rubber": ["object"], "small": ["object"], "right": ["object", "object"], "gray": ["object"], "metal": ["object"], "large": ["object"]}, "elements": {"object": ["5-0", "5-1"], "label": ["sphere", "cylinder"]}, "interpretation": {"left": [["5-1", "5-0"]], "has_label": [["5-0", "sphere"], ["5-1", "cylinder"]], "brown": [["5-0"]], "rubber": [["5-0"]], "small": [["5-0"]], "right": [["5-0", "5-1"]], "gray": [["5-1"]], "metal": [["5-1"]], "large": [["5-1"]]}, "raw": {"scene": [{"id": "5-0", "position": [1.4079852104187012, 0.09036020189523697, 0.344754695892334], "color": "brown", "material": "rubber", "shape": "sphere", "size": "small"}, {"id": "5-1", "position": [0.07276130467653275, -0.020467348396778107, 0.6825169324874878], "color": "gray", "material": "metal", "shape": "cylinder", "size": "large"}]}}