{"sorts": ["object", "label"], "predicates": {"has_label": ["object", "label"], "blue": ["object"], "black": ["object"], "brown": ["object"], "white": ["object"], "silver": ["object"], "pink": ["object"], "red": ["object"], "long": ["object"], "mounted": ["object"], "large": ["object"], "of": ["object", "object"], "to_the_right_of": ["object", "object"], "to_the_left_of": ["object", "object"], "on": ["object", "object"], "watching": ["object", "object"]}, "elements": {"object": ["854579", "854580", "854560", "854561", "854562", "854564", "854565", "854566", "854567", "854568", "854576", "854559", "854572", "854571", "854570"], "label": ["cord", "floor", "television", "clock", "wall", "fireplace", "collar", "ring", "cord", "bag", "man", "dog", "bandana", "ear", "curtains"]}, "interpretation": {"has_label": [["854579", "cord"], ["854580", "floor"], ["854560", "television"], ["854561", "clock"], ["854562", "wall"], ["854564", "fireplace"], ["854565", "collar"], ["854566", "ring"], ["854567", "cord"], ["854568", "bag"], ["854576", "man"], ["854559", "dog"], ["854572", "bandana"], ["854571", "ear"], ["854570", "curtains"]], "blue": [["854565"]], "black": [["854560"], ["854567"]], "brown": [["854559"]], "white": [["854580"], ["854561"], ["854568"]], "silver": [["854566"]], "pink": [["854570"]], "red": [["854562"], ["854572"]], "long": [["854567"]], "mounted": [["854560"]], "large": [["854560"]], "of": [["854565", "854559"], ["854571", "854559"]], "to_the_right_of": [["854561", "854579"], ["854562", "854576"], ["854562", "854580"], ["854562", "854570"], ["854562", "854579"], ["854562", "854560"], ["854564", "854579"], ["854564", "854580"], ["854565", "854564"], ["854565", "854566"], ["854565", "854568"], ["854566", "854568"], ["854566", "854564"], ["854567", "854576"], ["854567", "854561"], ["854567", "854560"], ["854568", "854580"], ["854559", "854561"], ["854559", "854568"], ["854559", "854564"], ["854559", "854567"], ["854559", "854572"], ["854571", "854567"]], "to_the_left_of": [["854579", "854561"], ["854579", "854564"], ["854579", "854562"], ["854580", "854564"], ["854580", "854562"], ["854580", "854568"], ["854560", "854562"], ["854560", "854567"], ["854561", "854559"], ["854561", "854567"], ["854564", "854559"], ["854564", "854565"], ["854564", "854566"], ["854566", "854565"], ["854567", "854559"], ["854567", "854571"], ["854568", "854559"], ["854568", "854566"], ["854568", "854565"], ["854576", "854562"], ["854576", "854567"], ["854572", "854559"], ["854570", "854562"]], "on": [["854561", "854562"], ["854565", "854559"], ["854572", "854568"]], "watching": [["854559", "854560"]]}}