{"sorts": ["object", "label"], "predicates": {"left": ["object", "object"], "disequal": ["object", "object"], "has_label": ["object", "label"], "brown": ["object"], "rubber": ["object"], "small": ["object"], "same_color": ["object", "object"], "same_material": ["object", "object"], "same_size": ["object", "object"], "right": ["object", "object"], "purple": ["object"]}, "elements": {"object": ["5-0", "5-1", "5-2", "5-3"], "label": ["cube"]}, "interpretation": {"left": [["5-1", "5-0"], ["5-2", "5-0"], ["5-3", "5-0"], ["5-2", "5-1"], ["5-1", "5-3"], ["5-2", "5-3"]], "disequal": [["5-1", "5-0"], ["5-2", "5-0"], ["5-3", "5-0"], ["5-0", "5-1"], ["5-2", "5-1"], ["5-3", "5-1"], ["5-0", "5-2"], ["5-1", "5-2"], ["5-3", "5-2"], ["5-0", "5-3"], ["5-1", "5-3"], ["5-2", "5-3"]], "has_label": [["5-0", "cube"], ["5-1", "cube"], ["5-2", "cube"], ["5-3", "cube"]], "brown": [["5-0"], ["5-1"]], "rubber": [["5-0"], ["5-1"], ["5-2"], ["5-3"]], "small": [["5-0"], ["5-1"], ["5-2"], ["5-3"]], "same_color": [["5-1", "5-0"], ["5-0", "5-1"], ["5-3", "5-2"], ["5-2", "5-3"]], "same_material": [["5-1", "5-0"], ["5-2", "5-0"], ["5-3", "5-0"], ["5-0", "5-1"], ["5-2", "5-1"], ["5-3", "5-1"], ["5-0", "5-2"], ["5-1", "5-2"], ["5-3", "5-2"], ["5-0", "5-3"], ["5-1", "5-3"], ["5-2", "5-3"]], "same_size": [["5-1", "5-0"], ["5-2", "5-0"], ["5-3", "5-0"], ["5-0", "5-1"], ["5-2", "5-1"], ["5-3", "5-1"], ["5-0", "5-2"], ["5-1", "5-2"], ["5-3", "5-2"], ["5-0", "5-3"], ["5-1", "5-3"], ["5-2", "5-3"]], "right": [["5-0", "5-1"], ["5-3", "5-1"], ["5-0", "5-2"], ["5-1", "5-2"], ["5-3", "5-2"], ["5-0", "5-3"]], "purple": [["5-2"], ["5-3"]]}, "raw": {"scene": [{"id": "5-0", "position": [2.758709192276001, 0.1852971911430359, 0.36205989122390747], "color": "brown", "material": "rubber", "shape": "cube", "size": "small"}, {"id": "5-1", "position": [-0.043810226023197174, 0.07685329020023346, 0.35860389471054077], "color": "brown", "material": "rubber", "shape": "cube", "size": "small"}, {"id": "5-2", "position": [-1.4505888223648071, -0.10638230293989182, 0.35812026262283325], "color": "purple", "material": "rubber", "shape": "cube", "size": "small"}, {"id": "5-3", "position": [1.366068959236145, 0.15890741348266602, 0.35871684551239014], "color": "purple", "material": "rubber", "shape": "cube", "size": "small"}]}}