{"sorts": ["object", "label"], "predicates": {"ON": ["object", "object"], "subway": ["object"], "track": ["object"], "grey": ["object"], "long": ["object"], "electric": ["object"], "passenger": ["object"], "speed": ["object"], "conical": ["object"], "large": ["object"], "on": ["object"], "has_label": ["object", "label"], "compartment": ["object"], "blue": ["object"], "has": ["object", "object"], "to": ["object", "object"], "OF": ["object", "object"]}, "interpretation": {"ON": [["490590_155_307", "490589_38_177"], ["490596_239_307", "490594_177_363"], ["490591_130_439", "490598_53_408"]], "subway": [["490589_38_177"]], "track": [["490589_38_177"]], "grey": [["490589_38_177"]], "long": [["490589_38_177"]], "electric": [["490589_38_177"]], "passenger": [["490589_38_177"]], "speed": [["490589_38_177"]], "conical": [["490589_38_177"]], "large": [["490590_155_307"], ["490592_129_202"]], "on": [["490590_155_307"]], "has_label": [["490590_155_307", "light"], ["490589_38_177", "train"], ["490596_239_307", "logo"], ["490594_177_363", "front"], ["490591_130_439", "cord"], ["490598_53_408", "ground"], ["490592_129_202", "window"], ["490600_2_159", "left"]], "compartment": [["490594_177_363"]], "blue": [["490596_239_307"], ["490591_130_439"]], "has": [["490589_38_177", "490590_155_307"], ["490589_38_177", "490590_155_307"], ["490589_38_177", "490592_129_202"], ["490589_38_177", "490592_129_202"], ["490589_38_177", "490592_129_202"]], "to": [["490589_38_177", "490600_2_159"]], "OF": [["490590_155_307", "490589_38_177"], ["490590_155_307", "490589_38_177"]]}, "elements": {"object": ["490592_129_202", "490591_130_439", "490590_155_307", "490598_53_408", "490600_2_159", "490589_38_177", "490596_239_307", "490594_177_363"], "label": ["window", "logo", "front", "cord", "light", "ground", "left", "train"]}, "image": {"id": 2391221, "url": "https://cs.stanford.edu/people/rak248/VG_100K_2/2391221.jpg", "width": 375, "height": 500, "coco_id": 69614, "flickr_id": 8663299309}}