{"sorts": ["object", "label"], "predicates": {"has_label": ["object", "label"], "brown": ["object"], "white": ["object"], "silver": ["object"], "metal": ["object"], "plastic": ["object"], "below": ["object", "object"], "to_the_right_of": ["object", "object"], "to_the_left_of": ["object", "object"], "on": ["object", "object"], "above": ["object", "object"]}, "elements": {"object": ["837022", "837023", "837020", "837021", "837026", "837006", "837024", "837025", "837012", "837011", "837007", "837017", "837016", "837014", "837019", "837008"], "label": ["paper", "plate", "faucet", "paper", "window", "counter", "tiles", "wall", "pipes", "pipes", "cords", "shelf", "ceiling", "cabinet", "faucet", "wall"]}, "interpretation": {"has_label": [["837022", "paper"], ["837023", "plate"], ["837020", "faucet"], ["837021", "paper"], ["837026", "window"], ["837006", "counter"], ["837024", "tiles"], ["837025", "wall"], ["837012", "pipes"], ["837011", "pipes"], ["837007", "cords"], ["837017", "shelf"], ["837016", "ceiling"], ["837014", "cabinet"], ["837019", "faucet"], ["837008", "wall"]], "brown": [["837024"]], "white": [["837022"], ["837023"], ["837021"], ["837012"], ["837011"], ["837007"], ["837016"], ["837008"]], "silver": [["837006"]], "metal": [["837006"], ["837014"]], "plastic": [["837011"]], "below": [["837006", "837014"]], "to_the_right_of": [["837022", "837021"], ["837020", "837019"], ["837021", "837014"], ["837025", "837014"], ["837025", "837026"], ["837025", "837008"], ["837012", "837006"], ["837012", "837017"], ["837012", "837011"], ["837011", "837006"], ["837011", "837017"], ["837017", "837008"]], "to_the_left_of": [["837021", "837022"], ["837026", "837025"], ["837006", "837012"], ["837006", "837011"], ["837011", "837012"], ["837017", "837012"], ["837017", "837011"], ["837014", "837025"], ["837014", "837021"], ["837019", "837020"], ["837008", "837017"], ["837008", "837025"]], "on": [["837023", "837008"], ["837021", "837025"]], "above": [["837014", "837006"]]}}