{"sorts": ["object", "label"], "predicates": {"has_label": ["object", "label"], "long_sleeved": ["object"], "young": ["object"], "transparent": ["object"], "blue": ["object"], "black": ["object"], "outdoor": ["object"], "delicious": ["object"], "brown": ["object"], "white": ["object"], "eating": ["object"], "foamy": ["object"], "yellow": ["object"], "puffy": ["object"], "blond": ["object"], "tall": ["object"], "sitting": ["object"], "metal": ["object"], "long": ["object"], "plastic": ["object"], "in": ["object", "object"], "to_the_right_of": ["object", "object"], "reflected_in": ["object", "object"], "to_the_left_of": ["object", "object"], "on": ["object", "object"], "holding": ["object", "object"], "drinking_from": ["object", "object"], "wearing": ["object", "object"]}, "elements": {"object": ["318402", "318403", "318400", "318401", "318406", "318407", "318404", "318405", "318424", "318425", "318408", "318409", "318420", "318422", "318423", "318426", "318411", "318413", "318415", "318414", "318417", "318416", "318419", "318418"], "label": ["pan", "beer", "plate", "pizza", "shirt", "woman", "glass", "table", "head", "face", "hair", "umbrella", "building", "shirt", "tree", "nose", "straw", "eye", "dumpster", "guy", "crust", "woman", "window", "crust"]}, "interpretation": {"has_label": [["318402", "pan"], ["318403", "beer"], ["318400", "plate"], ["318401", "pizza"], ["318406", "shirt"], ["318407", "woman"], ["318404", "glass"], ["318405", "table"], ["318424", "head"], ["318425", "face"], ["318408", "hair"], ["318409", "umbrella"], ["318420", "building"], ["318422", "shirt"], ["318423", "tree"], ["318426", "nose"], ["318411", "straw"], ["318413", "eye"], ["318415", "dumpster"], ["318414", "guy"], ["318417", "crust"], ["318416", "woman"], ["318419", "window"], ["318418", "crust"]], "long_sleeved": [["318406"]], "young": [["318407"]], "transparent": [["318411"]], "blue": [["318406"]], "black": [["318402"]], "outdoor": [["318405"]], "delicious": [["318401"]], "brown": [["318403"], ["318408"], ["318413"]], "white": [["318400"], ["318422"]], "eating": [["318407"]], "foamy": [["318404"]], "yellow": [["318409"]], "puffy": [["318413"]], "blond": [["318416"]], "tall": [["318420"]], "sitting": [["318407"]], "metal": [["318405"]], "long": [["318408"]], "plastic": [["318411"]], "in": [["318403", "318404"], ["318401", "318402"]], "to_the_right_of": [["318402", "318400"], ["318402", "318417"], ["318400", "318403"], ["318400", "318404"], ["318401", "318417"], ["318401", "318400"], ["318406", "318404"], ["318406", "318422"], ["318407", "318416"], ["318407", "318422"], ["318407", "318409"], ["318405", "318404"], ["318405", "318403"], ["318424", "318409"], ["318424", "318422"], ["318424", "318416"], ["318425", "318422"], ["318425", "318409"], ["318425", "318416"], ["318408", "318413"], ["318408", "318425"], ["318408", "318426"], ["318420", "318419"], ["318420", "318407"], ["318420", "318424"], ["318420", "318423"], ["318423", "318426"], ["318423", "318425"], ["318423", "318424"], ["318423", "318408"], ["318426", "318413"], ["318426", "318416"], ["318411", "318404"], ["318413", "318416"], ["318415", "318419"], ["318415", "318407"], ["318415", "318406"], ["318414", "318419"], ["318414", "318407"], ["318417", "318404"], ["318417", "318418"], ["318417", "318403"], ["318418", "318404"], ["318418", "318403"]], "reflected_in": [["318409", "318419"]], "to_the_left_of": [["318403", "318418"], ["318403", "318417"], ["318403", "318405"], ["318403", "318400"], ["318400", "318402"], ["318400", "318401"], ["318406", "318415"], ["318407", "318414"], ["318407", "318420"], ["318407", "318415"], ["318404", "318405"], ["318404", "318406"], ["318404", "318418"], ["318404", "318417"], ["318404", "318411"], ["318404", "318400"], ["318424", "318423"], ["318424", "318420"], ["318425", "318423"], ["318425", "318408"], ["318408", "318423"], ["318409", "318424"], ["318409", "318407"], ["318409", "318425"], ["318422", "318425"], ["318422", "318424"], ["318422", "318407"], ["318422", "318406"], ["318423", "318420"], ["318426", "318408"], ["318426", "318423"], ["318413", "318408"], ["318413", "318426"], ["318417", "318402"], ["318417", "318401"], ["318416", "318407"], ["318416", "318424"], ["318416", "318426"], ["318416", "318425"], ["318416", "318413"], ["318419", "318415"], ["318419", "318420"], ["318419", "318414"], ["318418", "318417"]], "on": [["318400", "318405"], ["318404", "318405"]], "holding": [["318404", "318403"]], "drinking_from": [["318407", "318411"]], "wearing": [["318407", "318406"], ["318416", "318422"]]}}