{"sorts": ["object", "label"], "predicates": {"inside": ["object", "object"], "black": ["object"], "cardboard": ["object"], "brown": ["object"], "light tan": ["object"], "has_label": ["object", "label"], "has": ["object", "object"], "red": ["object"], "tree": ["object", "object"], "tan": ["object"], "carpeted": ["object"], "upholstered": ["object"], "have": ["object", "object"], "are inside": ["object", "object"], "metal": ["object"], "silver": ["object"], "by": ["object", "object"], "ON": ["object", "object"], "wood": ["object"], "light brown": ["object"], "blonde": ["object"], "for cat": ["object"], "cat toy": ["object"], "frog shaped": ["object"], "small": ["object"], "inside of": ["object", "object"], "portion of": ["object", "object"], "scratches": ["object", "object"], "scratching ": ["object"], "for": ["object", "object"], "has a": ["object", "object"], "made of": ["object", "object"], "for lifting": ["object"], "large": ["object"]}, "interpretation": {"inside": [["511484_180_62", "511485_189_137"], ["511484_180_62", "511485_189_137"], ["511484_180_62", "511485_189_137"]], "black": [["511485_189_137"], ["511493_36_262"]], "cardboard": [["511485_189_137"]], "brown": [["511484_180_62"], ["511487_278_37"]], "light tan": [["511484_180_62"]], "has_label": [["511484_180_62", "cat"], ["511485_189_137", "box"], ["511487_278_37", "bag"], ["511488_343_126", "handles"], ["511492_0_11", "carpet"], ["511493_36_262", "remote controls"], ["511494_47_273", "grey buttons"], ["511495_88_288", "blue buttons"], ["511486_11_211", "basket"], ["511497_209_179", "xhilaration"], ["511498_429_332", "toy"], ["511496_2_2", "floor"], ["511499_229_0", "paper"], ["511500_224_3", "box"], ["511501_206_87", "ears"], ["511506_435_1", "floor has"], ["511505_0_1", "post"], ["511504_46_30", "dumbell"], ["511489_46_22", "dumbells"]], "has": [["511487_278_37", "511488_343_126"], ["511500_224_3", "511499_229_0"], ["511487_278_37", "511488_343_126"], ["511484_180_62", "511501_206_87"], ["511486_11_211", "511493_36_262"], ["511485_189_137", "511484_180_62"]], "red": [["511487_278_37"]], "tree": [["511484_180_62", "511492_0_11"]], "tan": [["511492_0_11"]], "carpeted": [["511492_0_11"]], "upholstered": [["511492_0_11"]], "have": [["511493_36_262", "511494_47_273"], ["511493_36_262", "511495_88_288"]], "are inside": [["511493_36_262", "511486_11_211"]], "metal": [["511486_11_211"], ["511489_46_22"]], "silver": [["511486_11_211"], ["511489_46_22"]], "by": [["511485_189_137", "511497_209_179"]], "ON": [["511498_429_332", "511496_2_2"], ["511487_278_37", "511496_2_2"]], "wood": [["511496_2_2"]], "light brown": [["511496_2_2"]], "blonde": [["511496_2_2"]], "for cat": [["511498_429_332"]], "cat toy": [["511498_429_332"]], "frog shaped": [["511498_429_332"]], "small": [["511498_429_332"]], "inside of": [["511499_229_0", "511485_189_137"]], "portion of": [["511506_435_1", "511496_2_2"]], "scratches": [["511484_180_62", "511505_0_1"]], "scratching ": [["511505_0_1"]], "for": [["511498_429_332", "511484_180_62"]], "has a": [["511485_189_137", "511484_180_62"]], "made of": [["511504_46_30", "511489_46_22"], ["511487_278_37", "511499_229_0"]], "for lifting": [["511504_46_30"]], "large": [["511504_46_30"]]}, "elements": {"object": ["511499_229_0", "511504_46_30", "511487_278_37", "511495_88_288", "511500_224_3", "511505_0_1", "511501_206_87", "511484_180_62", "511497_209_179", "511498_429_332", "511492_0_11", "511496_2_2", "511494_47_273", "511486_11_211", "511485_189_137", "511493_36_262", "511489_46_22", "511506_435_1", "511488_343_126"], "label": ["basket", "paper", "carpet", "cat", "box", "xhilaration", "toy", "ears", "dumbell", "blue buttons", "grey buttons", "floor has", "post", "dumbells", "floor", "remote controls", "bag", "handles"]}, "image": {"id": 2387727, "url": "https://cs.stanford.edu/people/rak248/VG_100K_2/2387727.jpg", "width": 500, "height": 375, "coco_id": null, "flickr_id": 317583494}}