{"sorts": ["object", "label"], "predicates": {"has_label": ["object", "label"], "gray": ["object"], "clear": ["object"], "small": ["object"], "blue": ["object"], "brown": ["object"], "white": ["object"], "purple": ["object"], "little": ["object"], "tall": ["object"], "green": ["object"], "to_the_right_of": ["object", "object"], "to_the_left_of": ["object", "object"], "on": ["object", "object"], "standing_in": ["object", "object"], "wearing": ["object", "object"]}, "elements": {"object": ["4530799", "4530793", "4530790", "4530797", "4530795", "4530794", "4530810", "4530806", "4530780", "4530782", "4530783", "4530784", "4530807", "4530820", "4530805", "4530804", "4530826", "4530829", "4530809", "4530808", "4530778", "4530771", "4530773"], "label": ["suv", "bush", "truck", "child", "sky", "bush", "tree", "tree_branch", "baseball_bat", "road", "man", "ball", "tree_branch", "sneakers", "tree_branch", "hair", "pants", "telephone_pole", "tree", "tree_branch", "rock", "pavement", "shoe"]}, "interpretation": {"has_label": [["4530799", "suv"], ["4530793", "bush"], ["4530790", "truck"], ["4530797", "child"], ["4530795", "sky"], ["4530794", "bush"], ["4530810", "tree"], ["4530806", "tree_branch"], ["4530780", "baseball_bat"], ["4530782", "road"], ["4530783", "man"], ["4530784", "ball"], ["4530807", "tree_branch"], ["4530820", "sneakers"], ["4530805", "tree_branch"], ["4530804", "hair"], ["4530826", "pants"], ["4530829", "telephone_pole"], ["4530809", "tree"], ["4530808", "tree_branch"], ["4530778", "rock"], ["4530771", "pavement"], ["4530773", "shoe"]], "gray": [["4530806"], ["4530807"], ["4530805"], ["4530808"]], "clear": [["4530795"]], "small": [["4530793"], ["4530794"], ["4530778"]], "blue": [["4530795"]], "brown": [["4530804"]], "white": [["4530790"], ["4530826"]], "purple": [["4530780"]], "little": [["4530797"]], "tall": [["4530810"], ["4530806"], ["4530807"], ["4530805"], ["4530809"], ["4530808"]], "green": [["4530810"], ["4530809"]], "to_the_right_of": [["4530790", "4530794"], ["4530794", "4530829"], ["4530794", "4530783"], ["4530806", "4530807"], ["4530780", "4530793"], ["4530780", "4530799"], ["4530784", "4530826"], ["4530805", "4530807"], ["4530809", "4530794"], ["4530808", "4530810"], ["4530778", "4530783"], ["4530771", "4530783"]], "to_the_left_of": [["4530799", "4530780"], ["4530793", "4530780"], ["4530794", "4530809"], ["4530794", "4530790"], ["4530810", "4530808"], ["4530783", "4530794"], ["4530783", "4530771"], ["4530783", "4530778"], ["4530807", "4530806"], ["4530807", "4530805"], ["4530826", "4530784"], ["4530829", "4530794"]], "on": [["4530797", "4530782"]], "standing_in": [["4530797", "4530782"]], "wearing": [["4530783", "4530826"]]}}