{"info": "clevr derendered scene", "scenes": [{"image_index": 0, "image_filename": "CLEVR_val_000000.png", "objects": [{"shape": "cube", "size": "large", "material": "metal", "color": "purple", "position": [2.7492082118988037, 0.22976571321487427, 0.6972537636756897]}, {"shape": "sphere", "size": "large", "material": "metal", "color": "purple", "position": [-0.023092754185199738, -0.058044496923685074, 0.6900553107261658]}]}, {"image_index": 1, "image_filename": "CLEVR_val_000001.png", "objects": [{"shape": "cube", "size": "large", "material": "metal", "color": "brown", "position": [0.05059197545051575, 0.003189604729413986, 0.6917174458503723]}, {"shape": "cube", "size": "large", "material": "metal", "color": "purple", "position": [-2.748645305633545, -0.18173116445541382, 0.696000874042511]}, {"shape": "sphere", "size": "large", "material": "metal", "color": "purple", "position": [2.94912052154541, 0.10009032487869263, 0.6940802931785583]}]}, {"image_index": 2, "image_filename": "CLEVR_val_000002.png", "objects": [{"shape": "sphere", "size": "large", "material": "metal", "color": "brown", "position": [2.8273136615753174, 0.25019946694374084, 0.696918249130249]}, {"shape": "cube", "size": "large", "material": "metal", "color": "purple", "position": [-0.09232815355062485, 0.0999586433172226, 0.6912398934364319]}, {"shape": "sphere", "size": "large", "material": "metal", "color": "purple", "position": [-2.9735333919525146, -0.20025646686553955, 0.6993108987808228]}]}, {"image_index": 3, "image_filename": "CLEVR_val_000003.png", "objects": [{"shape": "cube", "size": "small", "material": "metal", "color": "red", "position": [-1.3767815828323364, 0.025192540138959885, 0.35351961851119995]}, {"shape": "sphere", "size": "small", "material": "metal", "color": "red", "position": [1.2976795434951782, 0.1204230859875679, 0.3508666753768921]}, {"shape": "sphere", "size": "small", "material": "metal", "color": "red", "position": [-0.12637531757354736, 0.1325213611125946, 0.3531841039657593]}, {"shape": "sphere", "size": "small", "material": "metal", "color": "red", "position": [-2.8136088848114014, -0.15604355931282043, 0.35166504979133606]}]}, {"image_index": 4, "image_filename": "CLEVR_val_000004.png", "objects": [{"shape": "cylinder", "size": "large", "material": "metal", "color": "purple", "position": [-3.369593858718872, -0.20192337036132812, 0.6895667910575867]}, {"shape": "cube", "size": "large", "material": "metal", "color": "yellow", "position": [1.4097810983657837, 0.22511938214302063, 0.6975113153457642]}, {"shape": "sphere", "size": "large", "material": "metal", "color": "yellow", "position": [-1.3643878698349, -0.08812160044908524, 0.6933548450469971]}, {"shape": "sphere", "size": "large", "material": "metal", "color": "yellow", "position": [3.3214619159698486, 0.31631606817245483, 0.69678795337677]}]}, {"image_index": 5, "image_filename": "CLEVR_val_000005.png", "objects": [{"shape": "cylinder", "size": "large", "material": "metal", "color": "brown", "position": [2.920712947845459, 0.1513212025165558, 0.693932056427002]}, {"shape": "cube", "size": "large", "material": "metal", "color": "cyan", "position": [0.030004434287548065, -0.08126619458198547, 0.6920511722564697]}, {"shape": "sphere", "size": "large", "material": "metal", "color": "cyan", "position": [-2.7828269004821777, -0.20456579327583313, 0.7001074552536011]}]}]}