{"sorts": ["object", "label"], "predicates": {"left": ["object", "object"], "right": ["object", "object"], "disequal": ["object", "object"], "has_label": ["object", "label"], "brown": ["object"], "metal": ["object"], "small": ["object"], "same_color": ["object", "object"], "same_material": ["object", "object"], "same_size": ["object", "object"], "purple": ["object"]}, "elements": {"object": ["2-0", "2-1", "2-2", "2-3"], "label": ["sphere"]}, "interpretation": {"left": [["2-2", "2-0"], ["2-0", "2-1"], ["2-2", "2-1"], ["2-3", "2-1"], ["2-0", "2-3"], ["2-2", "2-3"]], "right": [["2-1", "2-0"], ["2-3", "2-0"], ["2-0", "2-2"], ["2-1", "2-2"], ["2-3", "2-2"], ["2-1", "2-3"]], "disequal": [["2-1", "2-0"], ["2-2", "2-0"], ["2-3", "2-0"], ["2-0", "2-1"], ["2-2", "2-1"], ["2-3", "2-1"], ["2-0", "2-2"], ["2-1", "2-2"], ["2-3", "2-2"], ["2-0", "2-3"], ["2-1", "2-3"], ["2-2", "2-3"]], "has_label": [["2-0", "sphere"], ["2-1", "sphere"], ["2-2", "sphere"], ["2-3", "sphere"]], "brown": [["2-0"], ["2-1"]], "metal": [["2-0"], ["2-1"], ["2-2"], ["2-3"]], "small": [["2-0"], ["2-1"], ["2-2"], ["2-3"]], "same_color": [["2-1", "2-0"], ["2-0", "2-1"], ["2-3", "2-2"], ["2-2", "2-3"]], "same_material": [["2-1", "2-0"], ["2-2", "2-0"], ["2-3", "2-0"], ["2-0", "2-1"], ["2-2", "2-1"], ["2-3", "2-1"], ["2-0", "2-2"], ["2-1", "2-2"], ["2-3", "2-2"], ["2-0", "2-3"], ["2-1", "2-3"], ["2-2", "2-3"]], "same_size": [["2-1", "2-0"], ["2-2", "2-0"], ["2-3", "2-0"], ["2-0", "2-1"], ["2-2", "2-1"], ["2-3", "2-1"], ["2-0", "2-2"], ["2-1", "2-2"], ["2-3", "2-2"], ["2-0", "2-3"], ["2-1", "2-3"], ["2-2", "2-3"]], "purple": [["2-2"], ["2-3"]]}, "raw": {"scene": [{"id": "2-0", "position": [-1.3858574628829956, -0.04583285003900528, 0.3782707452774048], "color": "brown", "material": "metal", "shape": "sphere", "size": "small"}, {"id": "2-1", "position": [1.3377583026885986, 0.12936097383499146, 0.38437986373901367], "color": "brown", "material": "metal", "shape": "sphere", "size": "small"}, {"id": "2-2", "position": [-2.890162229537964, -0.08163335174322128, 0.3948048949241638], "color": "purple", "material": "metal", "shape": "sphere", "size": "small"}, {"id": "2-3", "position": [-0.009975381195545197, 0.04522076994180679, 0.405656635761261], "color": "purple", "material": "metal", "shape": "sphere", "size": "small"}]}}